Workbook

Sheet FACTURA
A1: FACTURA · MODELO RESUELTO
A3: N.º factura | B3: F-2026-014
A4: Fecha | B4: 46321
A5: Cliente | B5: Oficina Norte, S. L.
A6: NIF | B6: B12345678
A9: Código | B9: Descripción | C9: Cantidad | D9: Precio unitario | E9: IVA | F9: Importe base
A10: S01 | B10: =IF(A10="","",IFERROR(VLOOKUP(A10,PRODUCTOS!$A$2:$D$15,2,FALSE),"Código no encontrado")) -> Mantenimiento informático | C10: 2 | D10: =IF(A10="","",IFERROR(VLOOKUP(A10,PRODUCTOS!$A$2:$D$15,3,FALSE),"")) -> 85 | E10: =IF(A10="","",IFERROR(VLOOKUP(A10,PRODUCTOS!$A$2:$D$15,4,FALSE),"")) -> 0.21 | F10: =C10*D10 -> 170
A11: S02 | B11: =IF(A11="","",IFERROR(VLOOKUP(A11,PRODUCTOS!$A$2:$D$15,2,FALSE),"Código no encontrado")) -> Instalación de software | C11: 1 | D11: =IF(A11="","",IFERROR(VLOOKUP(A11,PRODUCTOS!$A$2:$D$15,3,FALSE),"")) -> 120 | E11: =IF(A11="","",IFERROR(VLOOKUP(A11,PRODUCTOS!$A$2:$D$15,4,FALSE),"")) -> 0.21 | F11: =C11*D11 -> 120
A12: P01 | B12: =IF(A12="","",IFERROR(VLOOKUP(A12,PRODUCTOS!$A$2:$D$15,2,FALSE),"Código no encontrado")) -> Teclado USB | C12: 3 | D12: =IF(A12="","",IFERROR(VLOOKUP(A12,PRODUCTOS!$A$2:$D$15,3,FALSE),"")) -> 19.9 | E12: =IF(A12="","",IFERROR(VLOOKUP(A12,PRODUCTOS!$A$2:$D$15,4,FALSE),"")) -> 0.21 | F12: =C12*D12 -> 59.7
A13: P02 | B13: =IF(A13="","",IFERROR(VLOOKUP(A13,PRODUCTOS!$A$2:$D$15,2,FALSE),"Código no encontrado")) -> Ratón inalámbrico | C13: 2 | D13: =IF(A13="","",IFERROR(VLOOKUP(A13,PRODUCTOS!$A$2:$D$15,3,FALSE),"")) -> 24.5 | E13: =IF(A13="","",IFERROR(VLOOKUP(A13,PRODUCTOS!$A$2:$D$15,4,FALSE),"")) -> 0.21 | F13: =C13*D13 -> 49
A14: S03 | B14: =IF(A14="","",IFERROR(VLOOKUP(A14,PRODUCTOS!$A$2:$D$15,2,FALSE),"Código no encontrado")) -> Configuración de red | C14: 1 | D14: =IF(A14="","",IFERROR(VLOOKUP(A14,PRODUCTOS!$A$2:$D$15,3,FALSE),"")) -> 95 | E14: =IF(A14="","",IFERROR(VLOOKUP(A14,PRODUCTOS!$A$2:$D$15,4,FALSE),"")) -> 0.21 | F14: =C14*D14 -> 95
E16: Subtotal | F16: =SUM(F10:F14) -> 493.7
E17: IVA (21 %) | F17: =SUMPRODUCT(F10:F14,E10:E14) -> 103.677
E18: TOTAL FACTURA | F18: =F16+F17 -> 597.377
A20: Forma de pago | B20: Transferencia
A23: Ejercicio resuelto: modificar los datos y guardar como plantilla .xltx

Sheet LISTAS
A1: FORMAS DE PAGO
A2: Transferencia
A3: Tarjeta
A4: Efectivo
A5: Domiciliación

Sheet PRODUCTOS
A1: Código | B1: Descripción | C1: Precio unitario | D1: IVA
A2: S01 | B2: Mantenimiento informático | C2: 85 | D2: 0.21
A3: S02 | B3: Instalación de software | C3: 120 | D3: 0.21
A4: P01 | B4: Teclado USB | C4: 19.9 | D4: 0.21
A5: P02 | B5: Ratón inalámbrico | C5: 24.5 | D5: 0.21
A6: S03 | B6: Configuración de red | C6: 95 | D6: 0.21
A7: P03 | B7: Monitor 24 pulgadas | C7: 149 | D7: 0.21
A8: P04 | B8: Memoria USB 64 GB | C8: 12.5 | D8: 0.21
A9: P05 | B9: Disco SSD 500 GB | C9: 59 | D9: 0.21
A10: P06 | B10: Cable HDMI | C10: 9.9 | D10: 0.21
A11: S04 | B11: Asistencia remota | C11: 45 | D11: 0.21
A12: S05 | B12: Copia de seguridad | C12: 65 | D12: 0.21
A13: P07 | B13: Webcam HD | C13: 34.9 | D13: 0.21
... A15: S06 | B15: Limpieza y puesta a punto | C15: 55 | D15: 0.21
